donation_management/__init__.py
donation_management/utils.py
tests/__init__.py
tests/test_utils.py
donation_management-0.1.dist-info/LICENSE
donation_management-0.1.dist-info/METADATA
donation_management-0.1.dist-info/WHEEL
donation_management-0.1.dist-info/top_level.txt
donation_management-0.1.dist-info/RECORD
